{"stats":{"minecraft:custom":{"minecraft:jump":79,"minecraft:time_since_rest":667,"minecraft:deaths":2,"minecraft:damage_dealt":180,"minecraft:damage_taken":1060,"minecraft:leave_game":7,"minecraft:play_time":3887,"minecraft:sprint_one_cm":12209,"minecraft:time_since_death":644,"minecraft:walk_one_cm":6157,"minecraft:total_world_time":4054,"minecraft:mob_kills":16,"minecraft:fly_one_cm":36571},"minecraft:used":{"the_last_sword:the_last_sword":10},"minecraft:picked_up":{"the_last_sword:the_last_sword":2,"minecraft:slime_ball":2,"minecraft:mutton":2,"minecraft:white_wool":1,"minecraft:dirt":10},"minecraft:killed":{"minecraft:sheep":1,"minecraft:slime":15},"minecraft:mined":{"minecraft:grass_block":4,"minecraft:dirt":3}},"DataVersion":3465}